django_processengine-0.1.1.dist-info/DESCRIPTION.rst
django_processengine-0.1.1.dist-info/METADATA
django_processengine-0.1.1.dist-info/RECORD
django_processengine-0.1.1.dist-info/WHEEL
django_processengine-0.1.1.dist-info/metadata.json
django_processengine-0.1.1.dist-info/top_level.txt
processengine/__init__.py
processengine/admin.py
processengine/api.py
processengine/apps.py
processengine/models.py
processengine/signals.py
processengine/tasks.py
processengine/views.py
processengine/migrations/0001_initial.py
processengine/migrations/__init__.py
processengine/tests/__init__.py
processengine/tests/datas.py
processengine/tests/makers.py
processengine/tests/test_api.py
processengine/tests/test_models.py
tests/__init__.py
tests/datas.py
tests/makers.py
tests/test_api.py
tests/test_models.py
tests/test_settings.py
